{"ena":[["enable",[[2,3],[2,0],[2,1]]]],"sho":[["show",[[0,0]]]],"exa":[["example",[[0,1],[0,0]]]],"rdl":[["rdl",[[0,1],[0,0]]]],"rep":[["represents",[[1,2],[1,10]]]],"sit":[["situations",[[0,0]]]],"chi":[["chip",[[1,1]]],["chips",[[1,2],[1,10]]]],"add":[["address",[[0,0]]]],"uti":[["utilized",[[0,0]]]],"var":[["various",[[0,0]]]],"par":[["part",[[1,0],[1,1],[1,10]]]],"per":[["peripheral",[[2,0]]]],"wri":[["write",[[2,0]]]],"tog":[["toggle",[[2,3],[2,0]]]],"cot":[["cotains",[[1,0]]]],"asi":[["asic",[[1,0]]]],"rev":[["revision",[[1,0],[1,1],[1,2]]]],"fie":[["field",[[1,2],[1,10]]]],"num":[["number",[[1,1],[1,2],[1,10]]]],"con":[["contains",[[0,0]]]],"map":[["map",[[0,0]]]],"reg":[["register",[[1,0],[2,1]]],["registers",[[0,1],[0,0]]]],"xyz":[["xyz",[[1,0]]]]}